dlbar/__init__.py
dlbar/dlbar.py
dlbar-1.0.0.dist-info/LICENSE
dlbar-1.0.0.dist-info/METADATA
dlbar-1.0.0.dist-info/WHEEL
dlbar-1.0.0.dist-info/dependency_links.txt
dlbar-1.0.0.dist-info/top_level.txt
dlbar-1.0.0.dist-info/RECORD
