Metadata-Version: 2.1
Name: dlbar
Version: 1.0.0
Summary: dlbar is a simple terminal progress bar for downloading and displaying download progress.
Home-page: https://github.com/mimseyedi/dlbar
Author: mimseyedi
Author-email: mim.seyedi@gmail.com
License: MIT
Classifier: License :: OSI Approved :: MIT License
Classifier: Environment :: Console
Classifier: Intended Audience :: Developers
Classifier: Topic :: Utilities
Classifier: Programming Language :: Python :: 3
Classifier: Programming Language :: Python :: 3.10
Classifier: Programming Language :: Python :: 3.11
Requires-Python: >=3.10
License-File: LICENSE
Requires-Dist: requests
